lutron_integration/__init__.py
lutron_integration/connection.py
lutron_integration/devices.py
lutron_integration/py.typed
lutron_integration/qse.py
lutron_integration/types.py
lutron_integration-0.0.0a1.dist-info/WHEEL
lutron_integration-0.0.0a1.dist-info/METADATA
lutron_integration-0.0.0a1.dist-info/RECORD
