Metadata-Version: 2.4
Name: lutron-integration
Version: 0.0.0a1
Summary: Lutron Integration Protocol client, focused on QS Standalone
Keywords: QSE-CI-NWK-E,Lutron,QS Standalone,Grafik Eye
Author: Andy Lutomirski
Author-email: Andy Lutomirski <luto@kernel.org>
License-Expression: MIT
Classifier: Development Status :: 3 - Alpha
Classifier: Intended Audience :: Developers
Classifier: Programming Language :: Python :: 3
Maintainer: Andy Lutomirski
Maintainer-email: Andy Lutomirski <luto@kernel.org>
Requires-Python: >=3.12
Project-URL: Repository, https://github.com/amluto/lutron-integration
